{
  "name": "sink-inst-status-logs",
  "config": {
    "connector.class": "io.confluent.connect.jdbc.JdbcSinkConnector",
    "connection.url": "jdbc:postgresql://dev-db:5432/pgdatabase",
    "connection.user": "oltp_user",
    "connection.password": "oltp_pwd",
    "auto.create": "false",
    "auto.evolve": "false",

    "tasks.max": "3",

    "topics": "inst.status-logs",
    "table.name.format": "oltp.machine_status_logs",
    "table.types": "TABLE,PARTITIONED TABLE",

    "insert.mode": "insert",
    "pk.mode": "none",

    "key.converter": "org.apache.kafka.connect.storage.StringConverter",
    "value.converter": "io.confluent.connect.avro.AvroConverter",
    "value.converter.schema.registry.url": "http://schema-registry:8081"
  }
}